{
  "m_GameObject": {
    "m_FileID": 0,
    "m_PathID": -4990926476655851274
  },
  "m_Enabled": 1,
  "m_Script": {
    "m_FileID": 0,
    "m_PathID": 6078370316984442699
  },
  "m_Name": "",
  "ViewID": 403,
  "formId": -1,
  "walkSpeed": 0.22,
  "runSpeed": 2.0999997,
  "Origin": {
    "m_FileID": 0,
    "m_PathID": 7579829460798655386
  },
  "Waist": {
    "m_FileID": 0,
    "m_PathID": 583515869987033025
  },
  "Head": {
    "m_FileID": 0,
    "m_PathID": -7277556373942070568
  },
  "ViewFBX": {
    "m_FileID": 0,
    "m_PathID": -3207416499195405252
  },
  "customCollisionTransforms": [],
  "attentionBonesTransformsIsSet": 1,
  "attentionBonesRotationLimitDegrees": 40.0,
  "attentionBonesPettingLimitDegrees": 15.0,
  "attentionBonesTransforms": [
    {
      "m_FileID": 0,
      "m_PathID": -7277556373942070568
    }
  ],
  "animator": {
    "m_FileID": 0,
    "m_PathID": 1515128797219183436
  },
  "isFlying": 0,
  "haloSocket": {
    "m_FileID": 0,
    "m_PathID": -6651663403683578670
  },
  "faceSocket": {
    "m_FileID": 0,
    "m_PathID": 3102412964044121462
  },
  "bodySocket": {
    "m_FileID": 0,
    "m_PathID": 195758640333350156
  },
  "groundSocket": {
    "m_FileID": 0,
    "m_PathID": 4257050677027919373
  },
  "centerSocket": {
    "m_FileID": 0,
    "m_PathID": -2861991226484109147
  },
  "feedingSocket": {
    "m_FileID": 0,
    "m_PathID": 5646555645699158317
  },
  "badgeSocket": {
    "m_FileID": 0,
    "m_PathID": 527051645963376671
  },
  "defaultContext": 0,
  "glowEffect": {
    "m_FileID": 0,
    "m_PathID": 0
  }
}