{
  "m_GameObject": {
    "m_FileID": 0,
    "m_PathID": -622801196270525691
  },
  "m_Enabled": 1,
  "m_Script": {
    "m_FileID": 0,
    "m_PathID": -3227642854647831317
  },
  "m_Name": "",
  "drivenMaterials": [
    {
      "m_FileID": 0,
      "m_PathID": -3302292987535370567
    },
    {
      "m_FileID": 0,
      "m_PathID": -5169441033057358587
    }
  ],
  "materialPropertyDriver": {
    "xformDatas": [
      {
        "xformDriver": {
          "m_FileID": 0,
          "m_PathID": -844457787335233357
        },
        "xformDriverAuto": {
          "m_FileID": 0,
          "m_PathID": 0
        },
        "xformDriverCustom": {
          "m_FileID": 0,
          "m_PathID": -844457787335233357
        },
        "isOverrideDriver": 1,
        "drivenProperty": {
          "m_FileID": 4,
          "m_PathID": -4448334258314495917
        },
        "isOverrideValues": 1,
        "_magnitude": 0.0,
        "_min": 0.0,
        "_max": 0.0,
        "uvColumns": 4,
        "uvRows": 4,
        "uvSets": 1,
        "uvIsStepped": 1,
        "DrivenPropertyIDs": [
          {
            "ID": 288,
            "type": 1,
            "block": 0
          }
        ]
      },
      {
        "xformDriver": {
          "m_FileID": 0,
          "m_PathID": -28311836575496044
        },
        "xformDriverAuto": {
          "m_FileID": 0,
          "m_PathID": -28311836575496044
        },
        "xformDriverCustom": {
          "m_FileID": 0,
          "m_PathID": -28311836575496044
        },
        "isOverrideDriver": 1,
        "drivenProperty": {
          "m_FileID": 5,
          "m_PathID": 903589827763124156
        },
        "isOverrideValues": 1,
        "_magnitude": 0.0,
        "_min": 0.0,
        "_max": 0.0,
        "uvColumns": 2,
        "uvRows": 4,
        "uvSets": 1,
        "uvIsStepped": 1,
        "DrivenPropertyIDs": [
          {
            "ID": 290,
            "type": 1,
            "block": 0
          }
        ]
      }
    ],
    "xformCache": [
      {
        "xformDriver": {
          "m_FileID": 0,
          "m_PathID": -844457787335233357
        },
        "xformDataIndices": [
          0
        ],
        "xformDataIndexList": [
          0
        ]
      },
      {
        "xformDriver": {
          "m_FileID": 0,
          "m_PathID": -28311836575496044
        },
        "xformDataIndices": [
          1
        ],
        "xformDataIndexList": [
          1
        ]
      }
    ],
    "drivenMeshRenderers": [
      {
        "Default": {
          "m_FileID": 0,
          "m_PathID": -8008909895505858410
        },
        "Custom": {
          "m_FileID": 0,
          "m_PathID": 0
        },
        "isOverride": 0
      },
      {
        "Default": {
          "m_FileID": 0,
          "m_PathID": -3279221963359282026
        },
        "Custom": {
          "m_FileID": 0,
          "m_PathID": 0
        },
        "isOverride": 0
      },
      {
        "Default": {
          "m_FileID": 0,
          "m_PathID": -556352046563943087
        },
        "Custom": {
          "m_FileID": 0,
          "m_PathID": 0
        },
        "isOverride": 0
      }
    ],
    "cachedRenderers": [
      {
        "m_FileID": 0,
        "m_PathID": -8008909895505858410
      },
      {
        "m_FileID": 0,
        "m_PathID": -3279221963359282026
      },
      {
        "m_FileID": 0,
        "m_PathID": -556352046563943087
      }
    ],
    "uvFaceA": {
      "isActive": 1,
      "uvStep": {
        "x": 0.5,
        "y": 0.25
      }
    },
    "uvFaceB": {
      "isActive": 0,
      "uvStep": {
        "x": "NaN",
        "y": "NaN"
      }
    },
    "uvDirectA": {
      "isActive": 1,
      "uvStep": {
        "x": 0.25,
        "y": 0.25
      }
    },
    "uvDirectB": {
      "isActive": 0,
      "uvStep": {
        "x": "NaN",
        "y": "NaN"
      }
    },
    "originalFaceJointY": 0.0,
    "angryFaceJointY": 4.0,
    "smileFaceJointY": 0.0,
    "extraFaceJointOverride": []
  }
}