{
  "m_GameObject": {
    "m_FileID": 0,
    "m_PathID": -8238891747644106960
  },
  "m_Enabled": 1,
  "m_Script": {
    "m_FileID": 0,
    "m_PathID": -1807076637517768406
  },
  "m_Name": "",
  "driverJoints": [
    {
      "m_FileID": 0,
      "m_PathID": -3587808732667770015
    }
  ],
  "jointCountOffset": 0,
  "drivenMat": {
    "m_FileID": 0,
    "m_PathID": -5897924011635265465
  },
  "uvFrames": {
    "x": 2.0,
    "y": 8.0,
    "z": 2.0
  },
  "uvOffsetRenderers": [
    {
      "m_FileID": 0,
      "m_PathID": -8555513924494976037
    },
    {
      "m_FileID": 0,
      "m_PathID": -2384959301910901330
    },
    {
      "m_FileID": 0,
      "m_PathID": 8470765037776181282
    },
    {
      "m_FileID": 0,
      "m_PathID": 8361686281661252172
    }
  ],
  "pokemonModel": {
    "m_FileID": 0,
    "m_PathID": -4910510437329877710
  },
  "overrideFaceAnimation": 1,
  "angryFaceJointYPositionOverride": 0.4,
  "smileFaceJointYPosition": 0.5,
  "mouthDriverJoint": {
    "m_FileID": 0,
    "m_PathID": 0
  },
  "angryMouthJointPositionOverride": 0.0
}