{
  "m_GameObject": {
    "m_FileID": 0,
    "m_PathID": 392767843120178724
  },
  "m_Enabled": 1,
  "m_Script": {
    "m_FileID": 0,
    "m_PathID": -1807076637517768406
  },
  "m_Name": "",
  "driverJoints": [
    {
      "m_FileID": 0,
      "m_PathID": 4313481636112037309
    }
  ],
  "jointCountOffset": 0,
  "drivenMat": {
    "m_FileID": 0,
    "m_PathID": -8684129274036111438
  },
  "uvFrames": {
    "x": 2.0,
    "y": 8.0,
    "z": 2.0
  },
  "uvOffsetRenderers": [
    {
      "m_FileID": 0,
      "m_PathID": -1763854694306123182
    },
    {
      "m_FileID": 0,
      "m_PathID": 3624247399767663750
    },
    {
      "m_FileID": 0,
      "m_PathID": 3746052782863186703
    }
  ],
  "pokemonModel": {
    "m_FileID": 0,
    "m_PathID": -300603798061210129
  },
  "overrideFaceAnimation": 1,
  "angryFaceJointYPositionOverride": 0.4,
  "smileFaceJointYPosition": 0.5,
  "mouthDriverJoint": {
    "m_FileID": 0,
    "m_PathID": 0
  },
  "angryMouthJointPositionOverride": 0.0
}