{
  "m_GameObject": {
    "m_FileID": 0,
    "m_PathID": -7943565274012877600
  },
  "m_Enabled": 1,
  "m_Script": {
    "m_FileID": 0,
    "m_PathID": -1807076637517768406
  },
  "m_Name": "",
  "driverJoints": [
    {
      "m_FileID": 0,
      "m_PathID": -2405912203905487361
    }
  ],
  "jointCountOffset": 0,
  "drivenMat": {
    "m_FileID": 1,
    "m_PathID": 6754323273953002802
  },
  "uvFrames": {
    "x": 2.0,
    "y": 8.0,
    "z": 2.0
  },
  "uvOffsetRenderers": [
    {
      "m_FileID": 0,
      "m_PathID": -3402546574976422791
    }
  ],
  "pokemonModel": {
    "m_FileID": 0,
    "m_PathID": 7118845340226192934
  },
  "overrideFaceAnimation": 1,
  "angryFaceJointYPositionOverride": 0.4,
  "smileFaceJointYPosition": 0.5,
  "mouthDriverJoint": {
    "m_FileID": 0,
    "m_PathID": 0
  },
  "angryMouthJointPositionOverride": 0.0
}