{
  "m_GameObject": {
    "m_FileID": 0,
    "m_PathID": 8388704156297029543
  },
  "m_Enabled": 1,
  "m_Script": {
    "m_FileID": 0,
    "m_PathID": -1807076637517768406
  },
  "m_Name": "",
  "driverJoints": [
    {
      "m_FileID": 0,
      "m_PathID": 5186143224793450036
    }
  ],
  "jointCountOffset": 0,
  "drivenMat": {
    "m_FileID": 0,
    "m_PathID": 4329989308021392550
  },
  "uvFrames": {
    "x": 2.0,
    "y": 8.0,
    "z": 2.0
  },
  "uvOffsetRenderers": [
    {
      "m_FileID": 0,
      "m_PathID": 7864375450972889638
    },
    {
      "m_FileID": 0,
      "m_PathID": -8319329110963315871
    }
  ],
  "pokemonModel": {
    "m_FileID": 0,
    "m_PathID": 376805711697608697
  },
  "overrideFaceAnimation": 1,
  "angryFaceJointYPositionOverride": 0.4,
  "smileFaceJointYPosition": 0.5,
  "mouthDriverJoint": {
    "m_FileID": 0,
    "m_PathID": 0
  },
  "angryMouthJointPositionOverride": 0.0
}